CHANGES.txt
LICENSE.txt
MANIFEST.in
README.rst
README.txt
requirements.txt
setup.cfg
setup.py
win7ools/__init__.py
win7ools/ipl.py
win7ools/lib.py
win7ools/pdf.py
win7ools/reg.py
win7ools/sec.py
win7ools/this.py
win7ools/web.py
win7ools.egg-info/PKG-INFO
win7ools.egg-info/SOURCES.txt
win7ools.egg-info/dependency_links.txt
win7ools.egg-info/entry_points.txt
win7ools.egg-info/requires.txt
win7ools.egg-info/top_level.txt
win7ools/system/__init__.py