Metadata-Version: 1.1
Name: win7ools
Version: 0.3.0
Summary: Python project that provides programmatic access to the Windows OS
Home-page: https://github.com/nexuslevel/Win7ools
Author: Jason Wohlgemuth
Author-email: jason.h.wohlgemuth@gmail.com
License: MIT
Keywords: programmatic,access,automation,customization,productivity
Platform: UNKNOWN
Classifier: Development Status :: 3 - Alpha
Classifier: Environment :: Win32 (MS Windows)
Classifier: Operating System :: Microsoft :: Windows :: Windows 7
Classifier: Programming Language :: Python :: Implementation :: CPython
Classifier: Topic :: Scientific/Engineering :: Artificial Intelligence
Classifier: Topic :: Security
Classifier: Topic :: System
Classifier: Topic :: Utilities
Classifier: Natural Language :: English
Classifier: Intended Audience :: Developers
Classifier: Intended Audience :: Information Technology
Classifier: Intended Audience :: Science/Research
Classifier: Intended Audience :: System Administrators
Classifier: License :: OSI Approved :: Apache Software License
Classifier: Programming Language :: Python :: 2.7
Classifier: Programming Language :: Python :: 3
